Metadata-Version: 1.0
Name: rtsp-curl
Version: 0.1
Summary: What the module does
Home-page: https://github.com/madyel/rtsp_curl
Author: MaDyEl
Author-email: email@domain.net
License: MIT
Platform: UNKNOWN
